README.md
setup.py
CachedFunc/CacheManager.py
CachedFunc/NotInCacheError.py
CachedFunc/__init__.py
CachedFunc.egg-info/PKG-INFO
CachedFunc.egg-info/SOURCES.txt
CachedFunc.egg-info/dependency_links.txt
CachedFunc.egg-info/requires.txt
CachedFunc.egg-info/top_level.txt
CachedFunc/CacheRepos/BaseCacheRepo.py
CachedFunc/CacheRepos/JsonRepo.py
CachedFunc/CacheRepos/MemRepo.py
CachedFunc/CacheRepos/RedisRepo.py
CachedFunc/CacheRepos/__init__.py
test/TestCacheManager.py
test/TestCacheRepos.py
test/__init__.py